algorithmics_utils-0.1.1.dist-info/METADATA
algorithmics_utils-0.1.1.dist-info/WHEEL
algorithmics_utils/__init__.py
algorithmics_utils/__init__.pyi
algorithmics_utils/py.typed
algorithmics_utils/algorithmics_utils.cpython-37m-aarch64-linux-gnu.so
algorithmics_utils-0.1.1.dist-info/RECORD
