Metadata-Version: 2.3
Name: algorithmics_utils
Version: 0.1.1
Summary: Python module to learn
Home-Page: https://github.com/FooKaDoO/Algorithmics-test-utils/
Author: FooKaDoO
Project-URL: Source Code, https://github.com/FooKaDoO/Algorithmics-test-utils/
